exorcism/__init__.py
exorcism/main.py
exorcism-1.0.1.dist-info/METADATA
exorcism-1.0.1.dist-info/WHEEL
exorcism-1.0.1.dist-info/top_level.txt
exorcism-1.0.1.dist-info/RECORD
