Metadata-Version: 2.1
Name: exorcism
Version: 1.0.1
Summary: A powerful package for terminal text manipulation
Author: notkiwy
Author-email: notkiwy <notkiwy@yahoo.com>
Project-URL: Homepage, https://github.com/NotKiwy/exorcism
Project-URL: Bug Tracker, https://github.com/NotKiwy/exorcism/issues
Classifier: Programming Language :: Python :: 3
Classifier: License :: OSI Approved :: MIT License
Classifier: Operating System :: OS Independent
Requires-Python: >=3.6
